linglit/__init__.py
linglit/__main__.py
linglit/bibtex.py
linglit/cli_util.py
linglit/util.py
linglit/base/__init__.py
linglit/cfg/glossa/glossa.csv
linglit/cfg/langsci/bibtool.rsc
linglit/cfg/langsci/texfile_titles.tsv
linglit/cldf/__init__.py
linglit/cldf/publication.py
linglit/cldf/repository.py
linglit/commands/__init__.py
linglit/commands/bib.py
linglit/commands/igt.py
linglit/commands/mergedbib.py
linglit/commands/update.py
linglit/glossa/__init__.py
linglit/glossa/cfg.py
linglit/glossa/publication.py
linglit/glossa/repository.py
linglit/glossa/xml.py
linglit/langsci/__init__.py
linglit/langsci/bibtex.py
linglit/langsci/catalog.py
linglit/langsci/cfg.py
linglit/langsci/examples.py
linglit/langsci/latex.py
linglit/langsci/publication.py
linglit/langsci/repository.py
linglit/langsci/texfixes.py
linglit/langsci/texsoup.py
linglit-1.7.1.dist-info/LICENSE
linglit-1.7.1.dist-info/METADATA
linglit-1.7.1.dist-info/WHEEL
linglit-1.7.1.dist-info/entry_points.txt
linglit-1.7.1.dist-info/top_level.txt
linglit-1.7.1.dist-info/RECORD
